{
  "grade": 4,
  "yearsRange": [ 2018, 2019, 2020, 2021, 2022, 2023, 2024, 2025 ],
  "cities": {
    "suvorovo": {
      "fullName": "Суворово",
      "shortName": "Суворово",
      "schools": {
        "400163": {
          "fullName": "СУ Никола Вапцаров",
          "shortName": "СУ Никола Вапцаров",
          "isPrivate": false,
          "belScore": [ 69.52, 62.19, 62.19, 49.61, 53.8, 49.85, 64.05, 45.26 ],
          "matScore": [ 62.93, 57.19, 57.19, 43.16, 41.0, 40.8, 51.88, 41.81 ],
          "belStudents": [ 42, 57, 57, 31, 23, 40, 29, 34 ],
          "matStudents": [ 41, 57, 57, 31, 22, 41, 29, 34 ]
        }
      }
    }
  }
}
