{"code":"1000330","fullName":"ОУ Проф. Марин Дринов","shortName":"ОУ Марин Дринов","isPrivate":false,"website":null,"city":{"slug":"kiustendil","name":"Кюстендил"},"yearsRange":[2018,2019,2020,2021,2022,2023,2024,2025],"grades":{"4":{"belScore":[84.69,85.26,85.26,67.57,71.14,65.05,65.06,70.32],"matScore":[87.85,76.64,76.64,49.46,48.56,55.23,60.85,61.26],"belStudents":[65,57,57,69,63,66,53,33],"matStudents":[65,58,58,69,61,66,53,33],"yearsRange":[2018,2019,2020,2021,2022,2023,2024,2025],"latestYear":2025,"nationalRank":593,"nationalTotal":852,"cityRank":4,"cityTotal":5,"medianRank":630,"medianAdjustedRank":621,"medianTotal":866,"medianEndYear":2025},"7":{"belScore":[30.75,51.74,49.73,54.36,43.25,47.62,43.22,47.7],"matScore":[23.58,26.08,27.84,29.89,21.36,24.03,27.67,28.97],"belStudents":[67,68,57,77,77,78,67,61],"matStudents":[67,70,58,77,77,79,67,61],"yearsRange":[2018,2019,2020,2021,2022,2023,2024,2025],"latestYear":2025,"nationalRank":611,"nationalTotal":850,"cityRank":4,"cityTotal":6,"medianRank":637,"medianAdjustedRank":630,"medianTotal":863,"medianEndYear":2025}}}
