{"code":"1302623","fullName":"СУ Нешо Бончев","shortName":"СУ Нешо Бончев","isPrivate":false,"website":null,"city":{"slug":"panagiurishte","name":"Панагюрище"},"yearsRange":[2018,2019,2020,2021,2022,2023,2024,2025],"grades":{"4":{"belScore":[61.07,74.46,74.46,79.24,74.75,76.62,74.52,70.97],"matScore":[67.36,73.46,73.46,65.43,55.2,63.8,64.58,64.86],"belStudents":[70,65,65,59,60,55,48,57],"matStudents":[70,65,65,58,60,55,48,57],"latestYear":2025,"nationalRank":555,"nationalTotal":852,"cityRank":3,"cityTotal":3,"medianRank":541,"medianAdjustedRank":534,"medianTotal":866,"medianEndYear":2025},"7":{"belScore":[36.43,59.76,48.89,57.41,60.77,56.61,57.84,59.05],"matScore":[29.12,28.22,24.96,30.68,36.28,30.13,39.45,37.12],"belStudents":[74,75,74,78,68,74,59,63],"matStudents":[73,75,73,77,68,74,60,62],"latestYear":2025,"nationalRank":418,"nationalTotal":850,"cityRank":1,"cityTotal":3,"medianRank":418,"medianAdjustedRank":412,"medianTotal":863,"medianEndYear":2025},"10":{"belScore":[null,null,60.35,60.35,51.64,64.03,55.84,63.35],"matScore":[null,null,25.19,25.19,39.05,30.29,27.41,46.11],"belStudents":[null,null,49,49,67,49,66,57],"matStudents":[null,null,48,48,66,50,64,56],"latestYear":2025,"nationalRank":84,"nationalTotal":806,"cityRank":1,"cityTotal":2,"medianRank":149,"medianAdjustedRank":145,"medianTotal":823,"medianEndYear":2025},"12":{"belScore":[5.159,4.79,4.98,5.12,4.6,4.48,4.88,4.62],"matScore":[5.304,4.882,5.26,5.27,4.132,3.93,4.335,4.71],"belStudents":[53,65,40,45,65,47,66,50],"matStudents":[53,64,40,45,65,49,66,54],"latestYear":2025,"nationalRank":198,"nationalTotal":798,"cityRank":1,"cityTotal":2,"medianRank":209,"medianAdjustedRank":207,"medianTotal":815,"medianEndYear":2025}}}
