{"code":"1602401","fullName":"ОУ Петър Бонев","shortName":"ОУ Петър Бонев","isPrivate":false,"website":null,"city":{"slug":"perushtitsa","name":"Перущица"},"yearsRange":[2018,2019,2020,2021,2022,2023,2024,2025],"grades":{"4":{"belScore":[62.16,76.02,76.02,61.89,57.61,53.11,63.22,49.55],"matScore":[74.44,71.89,71.89,50.3,44.57,38.71,55.31,42.58],"belStudents":[37,44,44,37,22,19,27,33],"matStudents":[36,45,45,37,21,19,26,32],"yearsRange":[2018,2019,2020,2021,2022,2023,2024,2025],"latestYear":2025,"nationalRank":768,"nationalTotal":852,"cityRank":1,"cityTotal":1,"medianRank":750,"medianAdjustedRank":740,"medianTotal":866,"medianEndYear":2025},"7":{"belScore":[30.53,47.86,35.22,46.42,40.14,44.53,47.14,32.59],"matScore":[27.88,21.62,24.42,38.99,21.28,22.45,37.38,21.78],"belStudents":[32,36,39,32,32,38,29,28],"matStudents":[33,37,39,32,33,38,29,28],"yearsRange":[2018,2019,2020,2021,2022,2023,2024,2025],"latestYear":2025,"nationalRank":728,"nationalTotal":850,"cityRank":1,"cityTotal":1,"medianRank":666,"medianAdjustedRank":658,"medianTotal":863,"medianEndYear":2025}}}
