{"code":"200234","fullName":"СУ Кирил и Методий","shortName":"СУ Кирил и Методий","isPrivate":false,"website":"http://sukim.bg","city":{"slug":"burgas","name":"Бургас"},"yearsRange":[2018,2019,2020,2021,2022,2023,2024,2025,2026],"grades":{"4":{"belScore":[90.85,95.23,95.23,86.36,85.63,83.96,87.82,82.33],"matScore":[93.64,94.67,94.67,78.76,74.2,78.05,82.13,81.55],"belStudents":[100,108,108,95,90,99,91,119],"matStudents":[99,107,107,95,90,99,91,119],"yearsRange":[2018,2019,2020,2021,2022,2023,2024,2025],"latestYear":2025,"nationalRank":161,"nationalTotal":852,"cityRank":6,"cityTotal":32,"medianRank":114,"medianAdjustedRank":110,"medianTotal":866,"medianEndYear":2025},"7":{"belScore":[41.84,61.41,65.95,66.71,64.61,67.52,71.42,69.75],"matScore":[33.1,43.68,44.55,46.31,46.45,43.87,52.37,55.13],"belStudents":[70,132,132,105,132,124,103,106],"matStudents":[69,133,132,105,132,124,103,106],"yearsRange":[2018,2019,2020,2021,2022,2023,2024,2025],"latestYear":2025,"nationalRank":159,"nationalTotal":850,"cityRank":10,"cityTotal":32,"medianRank":162,"medianAdjustedRank":159,"medianTotal":863,"medianEndYear":2025},"10":{"belScore":[39.46,39.46,39.46,39.46,35.49,43.78,50.61,48.66],"matScore":[19.7,19.7,19.7,19.7,21.38,21.22,22.74,22.15],"belStudents":[61,61,61,61,73,70,74,68],"matStudents":[60,60,60,60,72,54,56,34],"yearsRange":[2018,2019,2020,2021,2022,2023,2024,2025],"latestYear":2025,"nationalRank":373,"nationalTotal":806,"cityRank":14,"cityTotal":29,"medianRank":401,"medianAdjustedRank":392,"medianTotal":823,"medianEndYear":2025},"12":{"belScore":[4.192,3.97,3.79,3.74,3.56,3.36,3.87,3.89,4.17],"matScore":[4.668,4.092,3.95,4.35,3.679,3.59,4.042,4.293,4.033],"belStudents":[87,77,43,88,74,67,85,75,84],"matStudents":[87,78,43,90,72,69,85,78,84],"yearsRange":[2018,2019,2020,2021,2022,2023,2024,2025,2026],"latestYear":2026,"nationalRank":466,"nationalTotal":801,"cityRank":16,"cityTotal":29,"medianRank":467,"medianAdjustedRank":463,"medianTotal":819,"medianEndYear":2026}}}
