{"code":"200246","fullName":"Търговска гимназия","shortName":"Търговска гимназия","isPrivate":false,"website":"http://tg-bs.com","city":{"slug":"burgas","name":"Бургас"},"yearsRange":[2018,2019,2020,2021,2022,2023,2024,2025],"grades":{"10":{"belScore":[61.41,61.41,61.41,61.41,58.95,64.03,61.52,59.46],"matScore":[28.66,28.66,28.66,28.66,38.37,39.81,34.15,33.31],"belStudents":[158,158,158,158,153,177,160,158],"matStudents":[158,158,158,158,152,176,157,150],"latestYear":2025,"nationalRank":172,"nationalTotal":806,"cityRank":6,"cityTotal":29,"medianRank":137,"medianAdjustedRank":134,"medianTotal":823,"medianEndYear":2025},"12":{"belScore":[4.99,4.74,4.92,4.77,4.63,4.45,5.02,4.77],"matScore":[5.112,4.535,4.9,4.82,4.461,5.247,5.334,5.101],"belStudents":[149,152,155,152,156,159,154,178],"matStudents":[135,139,134,102,156,162,155,180],"latestYear":2025,"nationalRank":119,"nationalTotal":798,"cityRank":5,"cityTotal":28,"medianRank":66,"medianAdjustedRank":65,"medianTotal":815,"medianEndYear":2025}}}
