{"code":"2216001","fullName":"1 СУ Пенчо Славейков","shortName":"1 СУ","isPrivate":false,"website":"http://1sousofia.org","city":{"slug":"sofia","name":"София"},"yearsRange":[2018,2019,2020,2021,2022,2023,2024,2025],"grades":{"4":{"belScore":[77.17,82.81,82.81,88.68,80.44,79.96,84.93,82.3],"matScore":[83.4,81.46,81.46,77.77,69.78,75.28,78.67,86.71],"belStudents":[99,89,89,98,74,45,69,65],"matStudents":[100,89,89,98,74,44,69,64],"latestYear":2025,"nationalRank":80,"nationalTotal":852,"cityRank":53,"cityTotal":203,"medianRank":148,"medianAdjustedRank":144,"medianTotal":866,"medianEndYear":2025},"7":{"belScore":[41.74,68.91,72.19,68.78,65.93,68.32,65.37,71.14],"matScore":[43.39,48.96,53.66,52.6,49.16,45.15,52.2,56.0],"belStudents":[70,82,83,94,79,104,101,81],"matStudents":[70,82,83,93,79,104,101,81],"latestYear":2025,"nationalRank":143,"nationalTotal":850,"cityRank":79,"cityTotal":212,"medianRank":165,"medianAdjustedRank":162,"medianTotal":863,"medianEndYear":2025},"10":{"belScore":[54.86,54.86,54.86,54.86,57.84,64.97,63.73,66.96],"matScore":[18.79,18.79,18.79,18.79,52.85,29.42,32.29,63.42],"belStudents":[98,98,98,98,103,115,108,102],"matStudents":[98,98,98,98,103,113,108,93],"latestYear":2025,"nationalRank":29,"nationalTotal":806,"cityRank":15,"cityTotal":153,"medianRank":88,"medianAdjustedRank":87,"medianTotal":823,"medianEndYear":2025},"12":{"belScore":[4.483,4.47,4.54,4.36,4.3,4.33,4.87,4.86],"matScore":[4.805,4.51,4.46,4.64,4.651,4.801,5.209,5.275],"belStudents":[124,106,73,87,91,102,106,115],"matStudents":[124,106,73,86,91,101,104,115],"latestYear":2025,"nationalRank":85,"nationalTotal":798,"cityRank":37,"cityTotal":154,"medianRank":93,"medianAdjustedRank":92,"medianTotal":815,"medianEndYear":2025}}}
