{"code":"2222012","fullName":"12 СУ Цар Иван Асен II","shortName":"12 СУ","isPrivate":false,"website":"http://12sou-sofia.info","city":{"slug":"sofia","name":"София"},"yearsRange":[2018,2019,2020,2021,2022,2023,2024,2025],"grades":{"4":{"belScore":[87.23,91.33,91.33,81.31,83.51,84.31,81.47,84.45],"matScore":[88.55,88.83,88.83,72.12,75.34,78.1,81.72,84.99],"belStudents":[112,94,94,77,67,71,70,71],"matStudents":[110,94,94,77,67,71,69,71],"latestYear":2025,"nationalRank":73,"nationalTotal":852,"cityRank":48,"cityTotal":203,"medianRank":117,"medianAdjustedRank":113,"medianTotal":866,"medianEndYear":2025},"7":{"belScore":[39.83,69.0,65.69,70.61,68.97,69.42,66.18,69.64],"matScore":[41.04,53.27,51.16,58.29,52.74,52.01,58.16,59.96],"belStudents":[49,73,54,89,95,97,72,75],"matStudents":[49,73,54,89,95,97,72,75],"latestYear":2025,"nationalRank":129,"nationalTotal":850,"cityRank":74,"cityTotal":212,"medianRank":129,"medianAdjustedRank":127,"medianTotal":863,"medianEndYear":2025},"10":{"belScore":[57.59,57.59,57.59,57.59,57.27,62.53,62.54,60.78],"matScore":[23.58,23.58,23.58,23.58,27.11,36.44,36.1,37.8],"belStudents":[74,74,74,74,73,77,71,79],"matStudents":[74,74,74,74,72,76,70,76],"latestYear":2025,"nationalRank":127,"nationalTotal":806,"cityRank":46,"cityTotal":153,"medianRank":133,"medianAdjustedRank":130,"medianTotal":823,"medianEndYear":2025},"12":{"belScore":[4.519,4.55,4.48,4.55,4.37,4.45,4.98,4.88],"matScore":[4.974,4.42,4.66,4.73,4.758,4.757,5.173,5.251],"belStudents":[67,84,75,68,70,76,71,79],"matStudents":[67,86,75,67,71,74,71,79],"latestYear":2025,"nationalRank":86,"nationalTotal":798,"cityRank":38,"cityTotal":154,"medianRank":84,"medianAdjustedRank":83,"medianTotal":815,"medianEndYear":2025}}}
