{"code":"2308850","fullName":"НУ Тодор Влайков","shortName":"НУ Тодор Влайков","isPrivate":false,"website":null,"city":{"slug":"pirdop","name":"Пирдоп"},"yearsRange":[2018,2019,2020,2021,2022,2023,2024,2025],"grades":{"4":{"belScore":[61.5,64.91,64.91,74.14,73.29,67.42,75.21,69.82],"matScore":[73.39,67.32,67.32,57.93,54.93,53.82,71.02,67.36],"belStudents":[60,56,56,58,58,59,51,58],"matStudents":[59,56,56,58,58,59,49,57],"latestYear":2025,"nationalRank":542,"nationalTotal":852,"cityRank":1,"cityTotal":1,"medianRank":577,"medianAdjustedRank":570,"medianTotal":866,"medianEndYear":2025}}}
