{"code":"2400165","fullName":"ПГ по облекло и хранене","shortName":"ПГ по облекло","isPrivate":false,"website":"http://pgohsz.com","city":{"slug":"stara-zagora","name":"Стара Загора"},"yearsRange":[2018,2019,2020,2021,2022,2023,2024,2025,2026],"grades":{"10":{"belScore":[36.37,36.37,36.37,36.37,37.83,40.33,46.43,38.63],"matScore":[16.56,16.56,16.56,16.56,22.41,16.85,17.2,19.48],"belStudents":[90,90,90,90,99,97,98,96],"matStudents":[89,89,89,89,99,97,98,96],"yearsRange":[2018,2019,2020,2021,2022,2023,2024,2025],"latestYear":2025,"nationalRank":547,"nationalTotal":806,"cityRank":14,"cityTotal":19,"medianRank":544,"medianAdjustedRank":532,"medianTotal":823,"medianEndYear":2025},"12":{"belScore":[3.868,3.66,3.82,3.63,2.96,3.08,3.86,3.55,3.78],"matScore":[4.32,3.658,4.07,3.87,3.549,4.137,4.43,4.092,4.624],"belStudents":[101,107,61,90,53,91,86,82,100],"matStudents":[17,25,14,8,53,89,84,87,93],"yearsRange":[2018,2019,2020,2021,2022,2023,2024,2025,2026],"latestYear":2026,"nationalRank":433,"nationalTotal":801,"cityRank":12,"cityTotal":21,"medianRank":463,"medianAdjustedRank":459,"medianTotal":819,"medianEndYear":2026}}}
