{"code":"2400108","fullName":"Спортно у-ще Тодор Каблешков","shortName":"СпУ Т. Каблешков","isPrivate":false,"website":"http://sportno-sz.com","city":{"slug":"stara-zagora","name":"Стара Загора"},"yearsRange":[2018,2019,2020,2021,2022,2023,2024,2025,2026],"grades":{"7":{"belScore":[23.33,36.53,33.91,37.62,42.1,36.92,36.57,38.38],"matScore":[17.85,18.1,20.4,21.99,19.24,22.57,23.33,24.68],"belStudents":[38,40,29,25,26,32,22,24],"matStudents":[39,40,30,25,24,30,22,24],"yearsRange":[2018,2019,2020,2021,2022,2023,2024,2025],"latestYear":2025,"nationalRank":694,"nationalTotal":850,"cityRank":19,"cityTotal":22,"medianRank":720,"medianAdjustedRank":711,"medianTotal":863,"medianEndYear":2025},"10":{"belScore":[30.94,30.94,30.94,30.94,35.26,42.12,31.28,39.92],"matScore":[16.53,16.53,16.53,16.53,28.76,22.28,16.11,22.81],"belStudents":[47,47,47,47,35,34,38,37],"matStudents":[47,47,47,47,35,30,37,32],"yearsRange":[2018,2019,2020,2021,2022,2023,2024,2025],"latestYear":2025,"nationalRank":488,"nationalTotal":806,"cityRank":11,"cityTotal":19,"medianRank":569,"medianAdjustedRank":557,"medianTotal":823,"medianEndYear":2025},"12":{"belScore":[3.642,3.48,3.29,3.36,2.97,2.91,3.6,3.35,3.54],"matScore":[3.191,3.772,3.49,3.43,4.73,3.84,4.943,4.94,5.307],"belStudents":[29,47,35,27,26,52,47,42,26],"matStudents":[7,5,7,1,25,43,37,36,22],"yearsRange":[2018,2019,2020,2021,2022,2023,2024,2025,2026],"latestYear":2026,"nationalRank":341,"nationalTotal":801,"cityRank":8,"cityTotal":21,"medianRank":368,"medianAdjustedRank":365,"medianTotal":819,"medianEndYear":2026}}}
