{"code":"2520401","fullName":"ПГ Симеон Велчев","shortName":"ПГ Симеон Велчев","isPrivate":false,"website":null,"city":{"slug":"omurtag","name":"Омуртаг"},"yearsRange":[2018,2019,2020,2021,2022,2023,2024,2025],"grades":{"10":{"belScore":[null,null,43.7,43.7,41.95,36.57,38.38,33.35],"matScore":[null,null,25.62,25.62,32.08,31.06,28.37,18.07],"belStudents":[null,null,73,73,56,49,72,48],"matStudents":[null,null,73,73,56,49,72,48],"latestYear":2025,"nationalRank":639,"nationalTotal":806,"cityRank":2,"cityTotal":2,"medianRank":520,"medianAdjustedRank":510,"medianTotal":823,"medianEndYear":2025},"12":{"belScore":[4.208,4.01,3.73,3.94,3.56,3.62,3.71,4.0],"matScore":[4.479,4.723,4.57,5.07,3.475,3.79,3.488,4.085],"belStudents":[67,58,34,50,45,72,63,56],"matStudents":[63,58,33,50,43,72,56,56],"latestYear":2025,"nationalRank":469,"nationalTotal":798,"cityRank":1,"cityTotal":2,"medianRank":535,"medianAdjustedRank":530,"medianTotal":815,"medianEndYear":2025}}}
