{"code":"2841532","fullName":"СУ Пейо Яворов","shortName":"СУ Пейо Яворов","isPrivate":false,"website":null,"city":{"slug":"straldzha","name":"Стралджа"},"yearsRange":[2018,2019,2020,2021,2022,2023,2024,2025,2026],"grades":{"4":{"belScore":[73.61,67.93,67.93,47.06,52.83,58.33,54.39,55.07],"matScore":[71.11,69.07,69.07,44.97,54.17,69.63,69.72,69.56],"belStudents":[54,58,58,35,59,58,45,47],"matStudents":[54,59,59,35,59,58,44,47],"yearsRange":[2018,2019,2020,2021,2022,2023,2024,2025],"latestYear":2025,"nationalRank":638,"nationalTotal":852,"cityRank":1,"cityTotal":2,"medianRank":632,"medianAdjustedRank":623,"medianTotal":866,"medianEndYear":2025},"7":{"belScore":[25.2,38.2,42.55,42.22,43.69,53.14,28.93,49.21],"matScore":[26.53,22.3,39.32,46.12,35.33,52.05,43.99,60.06],"belStudents":[60,46,39,48,44,69,37,58],"matStudents":[60,46,39,47,43,69,37,58],"yearsRange":[2018,2019,2020,2021,2022,2023,2024,2025],"latestYear":2025,"nationalRank":273,"nationalTotal":850,"cityRank":1,"cityTotal":2,"medianRank":377,"medianAdjustedRank":371,"medianTotal":863,"medianEndYear":2025},"10":{"belScore":[null,null,44.33,44.33,40.21,39.61,29.93,55.6],"matScore":[null,null,51.74,51.74,46.2,46.46,36.27,48.58],"belStudents":[null,null,39,39,28,28,15,20],"matStudents":[null,null,38,38,28,26,15,20],"yearsRange":[2018,2019,2020,2021,2022,2023,2024,2025],"latestYear":2025,"nationalRank":101,"nationalTotal":806,"cityRank":1,"cityTotal":1,"medianRank":223,"medianAdjustedRank":218,"medianTotal":823,"medianEndYear":2025},"12":{"belScore":[4.013,4.06,4.74,2.79,4.66,4.07,4.23,4.0,2.4],"matScore":[4.29,4.069,4.73,2.71,4.67,3.973,3.9,4.229,2.0],"belStudents":[19,30,14,2,20,27,16,11,3],"matStudents":[19,27,14,2,20,26,16,11,3],"yearsRange":[2018,2019,2020,2021,2022,2023,2024,2025,2026],"latestYear":2026,"nationalRank":796,"nationalTotal":801,"cityRank":1,"cityTotal":1,"medianRank":709,"medianAdjustedRank":700,"medianTotal":819,"medianEndYear":2026}}}
