{
  "grade": 10,
  "firstYear": 2018,
  "lastYear": 2025,
  "cities": {
    "aitos": {
      "fullName": "Айтос",
      "shortName": "Айтос",
      "schools": {
        "200112": {
          "fullName": "СУ Христо Ботев",
          "shortName": "СУ Христо Ботев",
          "isPrivate": false,
          "belScore": [ null, null, 46.68, 46.68, 45.65, 47.13, 54.6, 56.63 ],
          "matScore": [ null, null, 40.11, 40.11, 36.71, 38.82, 34.98, 46.02 ],
          "belStudents": [ null, null, 56, 56, 49, 53, 51, 51 ],
          "matStudents": [ null, null, 56, 56, 49, 53, 51, 51 ]
        }
      }
    }
  }
}
