{
  "grade": 4,
  "firstYear": 2018,
  "lastYear": 2025,
  "cities": {
    "burgas": {
      "fullName": "Бургас",
      "shortName": "Бургас",
      "schools": {
        "200206": {
          "fullName": "ОУ Св. Kняз Борис І",
          "shortName": "ОУ Kняз Борис І",
          "isPrivate": false,
          "belScore": [ 87.65, 91.41, 91.41, 84.37, 81.83, 81.42, 82.02, 79.74 ],
          "matScore": [ 87.65, 87.33, 87.33, 73.34, 68.03, 72.72, 77.31, 74.19 ],
          "belStudents": [ 98, 131, 131, 94, 72, 83, 87, 61 ],
          "matStudents": [ 100, 131, 131, 94, 69, 82, 88, 61 ]
        }
      }
    }
  }
}
