{
  "grade": 4,
  "yearsRange": [ 2018, 2019, 2020, 2021, 2022, 2023, 2024, 2025 ],
  "cities": {
    "dobrich": {
      "fullName": "Добрич",
      "shortName": "Добрич",
      "schools": {
        "800004": {
          "fullName": "ОУ Никола Вапцаров",
          "shortName": "ОУ Н. Вапцаров",
          "isPrivate": false,
          "belScore": [ 41.18, 49.05, 49.05, 52.36, 28.15, 42.29, 24.15, null ],
          "matScore": [ 61.47, 66.5, 66.5, 42.57, 19.79, 49.36, 29.14, null ],
          "belStudents": [ 17, 21, 21, 14, 13, 7, 10, null ],
          "matStudents": [ 17, 20, 20, 14, 14, 7, 11, null ]
        }
      }
    }
  }
}
