{
  "grade": 7,
  "firstYear": 2018,
  "lastYear": 2025,
  "cities": {
    "knezha": {
      "fullName": "Кнежа",
      "shortName": "Кнежа",
      "schools": {
        "1501103": {
          "fullName": "ОУ Отец Паисий",
          "shortName": "ОУ Отец Паисий",
          "isPrivate": false,
          "belScore": [ 22.89, 52.41, 38.87, 34.0, 41.98, 46.39, 32.5, 37.38 ],
          "matScore": [ 18.89, 23.99, 30.17, 25.73, 22.31, 27.48, 22.42, 28.58 ],
          "belStudents": [ 19, 23, 31, 28, 25, 23, 18, 17 ],
          "matStudents": [ 19, 24, 30, 27, 26, 25, 18, 18 ]
        }
      }
    }
  }
}
