{
  "grade": 7,
  "yearsRange": [ 2018, 2019, 2020, 2021, 2022, 2023, 2024, 2025 ],
  "cities": {
    "haskovo": {
      "fullName": "Хасково",
      "shortName": "Хасково",
      "schools": {
        "2601008": {
          "fullName": "ОУ Климент Охридски",
          "shortName": "ОУ Кл. Охридски",
          "isPrivate": false,
          "belScore": [ 43.08, 64.74, 72.59, 68.98, 60.97, 67.84, 66.78, 66.78 ],
          "matScore": [ 41.21, 41.34, 57.6, 46.52, 39.4, 45.67, 49.75, 46.1 ],
          "belStudents": [ 87, 89, 96, 82, 90, 98, 76, 69 ],
          "matStudents": [ 87, 89, 96, 82, 90, 98, 76, 69 ]
        }
      }
    }
  }
}
