{
  "grade": 4,
  "yearsRange": [ 2018, 2019, 2020, 2021, 2022, 2023, 2024, 2025 ],
  "cities": {
    "cherven-briag": {
      "fullName": "Червен бряг",
      "shortName": "Червен бряг",
      "schools": {
        "1500215": {
          "fullName": "СУ Д-р Петър Берон",
          "shortName": "СУ Петър Берон",
          "isPrivate": false,
          "belScore": [ 63.53, 73.12, 73.12, 73.01, 70.36, 69.04, 78.86, 75.42 ],
          "matScore": [ 75.57, 68.28, 68.28, 55.2, 59.87, 60.27, 75.22, 77.37 ],
          "belStudents": [ 51, 93, 93, 74, 55, 73, 74, 69 ],
          "matStudents": [ 53, 93, 93, 74, 55, 73, 74, 69 ]
        }
      }
    }
  }
}
