{
  "grade": 12,
  "yearsRange": [ 2018, 2019, 2020, 2021, 2022, 2023, 2024, 2025 ],
  "cities": {
    "shumen": {
      "fullName": "Шумен",
      "shortName": "Шумен",
      "schools": {
        "2700076": {
          "fullName": "СУ Панайот Волов",
          "shortName": "СУ Панайот Волов",
          "isPrivate": false,
          "belScore": [ 4.279, 3.86, 4.09, 3.66, 4.22, 3.5, 4.53, 4.03 ],
          "matScore": [ 4.432, 3.957, 4.25, 4.07, 3.714, 3.81, 4.858, 4.454 ],
          "belStudents": [ 60, 60, 64, 51, 37, 65, 60, 71 ],
          "matStudents": [ 60, 60, 64, 51, 38, 68, 60, 70 ]
        }
      }
    }
  }
}
