{
  "grade": 7,
  "yearsRange": [ 2018, 2019, 2020, 2021, 2022, 2023, 2024, 2025 ],
  "cities": {
    "samokov": {
      "fullName": "Самоков",
      "shortName": "Самоков",
      "schools": {
        "2304610": {
          "fullName": "Спортно у-ще Никола Велчев",
          "shortName": "СпУ Никола Велчев",
          "isPrivate": false,
          "belScore": [ 23.2, 36.39, 30.61, 41.87, 34.96, 31.39, 36.83, 40.52 ],
          "matScore": [ 23.25, 12.43, 19.46, 17.66, 22.03, 15.7, 23.8, 22.31 ],
          "belStudents": [ 20, 22, 23, 35, 26, 23, 24, 25 ],
          "matStudents": [ 20, 22, 23, 35, 26, 22, 24, 24 ]
        }
      }
    }
  }
}
