{
  "grade": 7,
  "firstYear": 2018,
  "lastYear": 2025,
  "cities": {
    "teteven": {
      "fullName": "Тетевен",
      "shortName": "Тетевен",
      "schools": {
        "1100509": {
          "fullName": "СУ Георги Бенковски",
          "shortName": "СУ Георги Бенковски",
          "isPrivate": false,
          "belScore": [ 29.6, 53.33, 53.13, 54.72, 49.33, 50.17, 54.99, 49.09 ],
          "matScore": [ 21.74, 33.27, 30.32, 31.79, 25.01, 23.92, 40.03, 28.95 ],
          "belStudents": [ 61, 70, 61, 41, 57, 77, 59, 44 ],
          "matStudents": [ 61, 70, 61, 41, 57, 77, 59, 44 ]
        }
      }
    }
  }
}
