{
  "grade": 12,
  "yearsRange": [ 2018, 2019, 2020, 2021, 2022, 2023, 2024, 2025 ],
  "cities": {
    "vratsa": {
      "fullName": "Враца",
      "shortName": "Враца",
      "schools": {
        "608060": {
          "fullName": "Спортно у-ще Св. Климент Охридски",
          "shortName": "Спортно у-ще",
          "isPrivate": false,
          "belScore": [ 3.691, 3.19, 3.56, 3.42, 3.05, 2.77, 3.68, 3.56 ],
          "matScore": [ 3.805, 3.493, 3.74, 3.84, 5.07, 5.3, 5.31, 5.24 ],
          "belStudents": [ 32, 15, 41, 37, 41, 27, 26, 31 ],
          "matStudents": [ 34, 15, 40, 34, 39, 21, 20, 26 ]
        }
      }
    }
  }
}
