{
  "grade": 12,
  "yearsRange": [ 2018, 2019, 2020, 2021, 2022, 2023, 2024, 2025 ],
  "cities": {
    "knezha": {
      "fullName": "Кнежа",
      "shortName": "Кнежа",
      "schools": {
        "1501109": {
          "fullName": "ПГ по земеделие Стефан Цанов",
          "shortName": "ПГ по земеделие",
          "isPrivate": false,
          "belScore": [ 3.38, 3.24, 3.61, 3.54, 2.94, 3.0, 3.49, 3.78 ],
          "matScore": [ 4.267, 3.24, 5.11, null, 4.23, 4.506, 4.529, 5.068 ],
          "belStudents": [ 75, 54, 50, 59, 40, 55, 52, 50 ],
          "matStudents": [ 19, 2, 10, null, 38, 45, 48, 49 ]
        }
      }
    }
  }
}
