{
  "grade": 7,
  "firstYear": 2018,
  "lastYear": 2025,
  "cities": {
    "peshtera": {
      "fullName": "Пещера",
      "shortName": "Пещера",
      "schools": {
        "1301763": {
          "fullName": "ОУ Патриарх Евтимий",
          "shortName": "ОУ Патр. Евтимий",
          "isPrivate": false,
          "belScore": [ 28.9, 54.0, 52.18, 44.93, 42.4, 51.05, 50.44, 57.74 ],
          "matScore": [ 22.42, 30.63, 29.56, 21.92, 20.74, 38.64, 24.0, 28.03 ],
          "belStudents": [ 31, 44, 36, 34, 31, 11, 18, 19 ],
          "matStudents": [ 31, 44, 35, 33, 30, 11, 18, 19 ]
        }
      }
    }
  }
}
