{
  "grade": 7,
  "yearsRange": [ 2018, 2019, 2020, 2021, 2022, 2023, 2024, 2025 ],
  "cities": {
    "plovdiv": {
      "fullName": "Пловдив",
      "shortName": "Пловдив",
      "schools": {
        "1690346": {
          "fullName": "МГ Акад. Кирил Попов",
          "shortName": "МГ Акад. Кирил Попов",
          "isPrivate": false,
          "belScore": [ 55.67, 90.84, 90.11, 89.43, 91.33, 89.41, 88.27, 93.44 ],
          "matScore": [ 63.87, 94.25, 92.26, 92.46, 93.68, 93.54, 95.75, 95.27 ],
          "belStudents": [ 30, 29, 58, 55, 57, 86, 53, 52 ],
          "matStudents": [ 30, 30, 58, 55, 57, 86, 53, 52 ]
        }
      }
    }
  }
}
