{
  "grade": 12,
  "yearsRange": [ 2018, 2019, 2020, 2021, 2022, 2023, 2024, 2025 ],
  "cities": {
    "bobov-dol": {
      "fullName": "Бобов дол",
      "shortName": "Бобов дол",
      "schools": {
        "1002450": {
          "fullName": "Професионална гимназия",
          "shortName": "Професионална гимназия",
          "isPrivate": false,
          "belScore": [ null, 3.26, null, null, null, null, null, null ],
          "matScore": [ null, null, null, null, null, null, null, null ],
          "belStudents": [ null, 24, null, null, null, null, null, null ],
          "matStudents": [ null, null, null, null, null, null, null, null ]
        }
      }
    }
  }
}
