{
  "grade": 12,
  "firstYear": 2018,
  "lastYear": 2025,
  "cities": {
    "sofia": {
      "fullName": "София",
      "shortName": "София",
      "schools": {
        "2208413": {
          "fullName": "Софийска гимназия по хлебни/сладкарски технологии",
          "shortName": "Гимн. по хлебни техн.",
          "isPrivate": false,
          "belScore": [ 3.663, 3.5, 3.67, 3.35, 3.03, 3.15, 3.54, 3.25 ],
          "matScore": [ 3.926, 3.405, 3.71, 3.44, 4.53, 4.412, 5.044, 4.201 ],
          "belStudents": [ 57, 45, 48, 27, 26, 24, 28, 27 ],
          "matStudents": [ 53, 35, 38, 23, 23, 19, 24, 25 ]
        }
      }
    }
  }
}
