{
  "grade": 12,
  "firstYear": 2018,
  "lastYear": 2025,
  "cities": {
    "sofia": {
      "fullName": "София",
      "shortName": "София",
      "schools": {
        "2218071": {
          "fullName": "71 СУ Пейо Яворов",
          "shortName": "71 СУ",
          "isPrivate": false,
          "belScore": [ 3.785, 4.07, 3.95, 3.5, 2.79, 3.38, 3.28, 3.09 ],
          "matScore": [ 3.826, 4.572, 4.12, 3.86, 3.47, 3.546, 3.985, 3.441 ],
          "belStudents": [ 22, 13, 11, 21, 12, 16, 25, 24 ],
          "matStudents": [ 22, 12, 11, 19, 11, 16, 22, 21 ]
        }
      }
    }
  }
}
