{
  "grade": 7,
  "yearsRange": [ 2018, 2019, 2020, 2021, 2022, 2023, 2024, 2025 ],
  "cities": {
    "troyan": {
      "fullName": "Троян",
      "shortName": "Троян",
      "schools": {
        "1100612": {
          "fullName": "СУ Васил Левски",
          "shortName": "СУ Васил Левски",
          "isPrivate": false,
          "belScore": [ 37.09, 65.73, 55.72, 64.26, 62.1, 67.72, 55.56, 63.94 ],
          "matScore": [ 33.21, 36.36, 32.21, 33.82, 36.97, 35.99, 35.52, 42.93 ],
          "belStudents": [ 96, 96, 90, 75, 74, 90, 76, 76 ],
          "matStudents": [ 96, 96, 90, 75, 74, 90, 76, 76 ]
        }
      }
    }
  }
}
