{
  "grade": 7,
  "yearsRange": [ 2018, 2019, 2020, 2021, 2022, 2023, 2024, 2025 ],
  "cities": {
    "kotel": {
      "fullName": "Котел",
      "shortName": "Котел",
      "schools": {
        "2000201": {
          "fullName": "СУ Георги Раковски",
          "shortName": "СУ Георги Раковски",
          "isPrivate": false,
          "belScore": [ 25.03, 29.23, 36.29, 38.83, 32.89, 37.28, 40.33, 25.08 ],
          "matScore": [ 14.43, 15.13, 20.37, 21.35, 14.34, 15.95, 23.51, 17.09 ],
          "belStudents": [ 30, 35, 21, 36, 41, 25, 24, 19 ],
          "matStudents": [ 30, 36, 21, 34, 41, 24, 24, 19 ]
        }
      }
    }
  }
}
