{
  "grade": 10,
  "firstYear": 2018,
  "lastYear": 2025,
  "cities": {
    "burgas": {
      "fullName": "Бургас",
      "shortName": "Бургас",
      "schools": {
        "200236": {
          "fullName": "Английска ЕГ Гео Милев",
          "shortName": "Английска ЕГ",
          "isPrivate": false,
          "belScore": [ 62.04, 62.04, 62.04, 62.04, 61.49, 66.27, 65.53, 60.31 ],
          "matScore": [ 28.49, 28.49, 28.49, 28.49, 45.66, 46.6, 39.74, 41.58 ],
          "belStudents": [ 156, 156, 156, 156, 126, 161, 158, 157 ],
          "matStudents": [ 156, 156, 156, 156, 123, 154, 156, 153 ]
        }
      }
    }
  }
}
