{
  "grade": 4,
  "yearsRange": [ 2018, 2019, 2020, 2021, 2022, 2023, 2024, 2025 ],
  "cities": {
    "varna": {
      "fullName": "Варна",
      "shortName": "Варна",
      "schools": {
        "400031": {
          "fullName": "СУЕО Ал. С. Пушкин",
          "shortName": "СУЕО Пушкин",
          "isPrivate": false,
          "belScore": [ 85.74, 93.01, 93.01, 88.22, 84.54, 87.01, 88.26, 84.93 ],
          "matScore": [ 87.05, 90.9, 90.9, 74.15, 73.13, 78.09, 80.94, 82.32 ],
          "belStudents": [ 128, 148, 148, 106, 114, 110, 106, 101 ],
          "matStudents": [ 127, 145, 145, 106, 114, 111, 106, 100 ]
        }
      }
    }
  }
}
