{
  "grade": 10,
  "firstYear": 2018,
  "lastYear": 2025,
  "cities": {
    "sofia": {
      "fullName": "София",
      "shortName": "София",
      "schools": {
        "2220014": {
          "fullName": "14 СУ Проф. Д-р Асен Златаров",
          "shortName": "14 СУ",
          "isPrivate": false,
          "belScore": [ 34.43, 34.43, 34.43, 34.43, 39.25, 53.09, 43.29, 44.67 ],
          "matScore": [ 15.71, 15.71, 15.71, 15.71, 22.91, 22.3, 21.75, 20.78 ],
          "belStudents": [ 14, 14, 14, 14, 16, 23, 21, 24 ],
          "matStudents": [ 14, 14, 14, 14, 16, 23, 18, 23 ]
        }
      }
    }
  }
}
