{
  "grade": 10,
  "firstYear": 2018,
  "lastYear": 2025,
  "cities": {
    "shumen": {
      "fullName": "Шумен",
      "shortName": "Шумен",
      "schools": {
        "2700231": {
          "fullName": "СУ Васил Левски",
          "shortName": "СУ Васил Левски",
          "isPrivate": false,
          "belScore": [ 41.57, 41.57, 41.57, 41.57, 23.17, 38.72, 27.4, 34.0 ],
          "matScore": [ 22.69, 22.69, 22.69, 22.69, 16.67, 18.14, 18.28, 19.27 ],
          "belStudents": [ 14, 14, 14, 14, 12, 23, 25, 16 ],
          "matStudents": [ 13, 13, 13, 13, 12, 23, 25, 15 ]
        }
      }
    }
  }
}
